{
  "ts_col": "2025-10-15T23:56:19-05:00",
  "xau": {
    "swissquote": {
      "price": 4232.69,
      "bid": 4232.567,
      "ask": 4232.813,
      "ts_src": "2025-10-16T04:56:17+00:00",
      "ts_src_col": "2025-10-15T23:56:17-05:00",
      "platform": "SwissquoteCapitalMarkets",
      "server": "Live7",
      "profile": "elite",
      "note": "Swissquote mejor liquidez"
    },
    "institucional": {
      "price": 4232.69,
      "bid": null,
      "ask": null,
      "ts_src": null,
      "ts_src_col": null,
      "platform": null,
      "server": null,
      "profile": null,
      "note": "XAU: 100% Swissquote"
    },
    "volatility": {
      "atr_cc_14": 0.8487450742479764,
      "atr_pct": 0.020052143536332133,
      "range_24h_local": {
        "high": 4241.47,
        "low": 4229.695,
        "width": 11.775000000000546
      }
    }
  },
  "btc": {
    "coingecko": {
      "price": 111112.0,
      "bid": null,
      "ask": null,
      "ts_src": null,
      "ts_src_col": null,
      "platform": null,
      "server": null,
      "profile": null,
      "note": "CoinGecko simple/price"
    },
    "coinbase": {
      "price": 111080.605,
      "bid": null,
      "ask": null,
      "ts_src": null,
      "ts_src_col": null,
      "platform": null,
      "server": null,
      "profile": null,
      "note": "Coinbase Spot"
    },
    "institucional": {
      "price": 111099.442,
      "bid": null,
      "ask": null,
      "ts_src": null,
      "ts_src_col": null,
      "platform": null,
      "server": null,
      "profile": null,
      "note": "BTC: 60% CoinGecko + 40% Coinbase"
    },
    "volatility": {
      "atr_cc_14": 33.3487944285924,
      "atr_pct": 0.030017067438189653,
      "range_24h_local": {
        "high": 111782.486,
        "low": 110952.882,
        "width": 829.6040000000066
      }
    }
  }
}