{
  "ts_col": "2025-10-16T12:34:06-05:00",
  "xau": {
    "swissquote": {
      "price": 4291.815,
      "bid": 4291.692,
      "ask": 4291.938,
      "ts_src": "2025-10-16T17:33:32+00:00",
      "ts_src_col": "2025-10-16T12:33:32-05:00",
      "platform": "SwissquoteCapitalMarkets",
      "server": "Live7",
      "profile": "elite",
      "note": "Swissquote mejor liquidez"
    },
    "institucional": {
      "price": 4291.815,
      "bid": null,
      "ask": null,
      "ts_src": null,
      "ts_src_col": null,
      "platform": null,
      "server": null,
      "profile": null,
      "note": "XAU: 100% Swissquote"
    },
    "volatility": {
      "atr_cc_14": 1.6877327976321157,
      "atr_pct": 0.03932445358507102,
      "range_24h_local": {
        "high": 4294.47,
        "low": 4233.395,
        "width": 61.07499999999982
      }
    }
  },
  "btc": {
    "coingecko": {
      "price": 108789.0,
      "bid": null,
      "ask": null,
      "ts_src": null,
      "ts_src_col": null,
      "platform": null,
      "server": null,
      "profile": null,
      "note": "CoinGecko simple/price"
    },
    "coinbase": {
      "price": 108809.265,
      "bid": null,
      "ask": null,
      "ts_src": null,
      "ts_src_col": null,
      "platform": null,
      "server": null,
      "profile": null,
      "note": "Coinbase Spot"
    },
    "institucional": {
      "price": 108797.106,
      "bid": null,
      "ask": null,
      "ts_src": null,
      "ts_src_col": null,
      "platform": null,
      "server": null,
      "profile": null,
      "note": "BTC: 60% CoinGecko + 40% Coinbase"
    },
    "volatility": {
      "atr_cc_14": 77.4041697729515,
      "atr_pct": 0.07114543081040363,
      "range_24h_local": {
        "high": 111642.788,
        "low": 107801.07,
        "width": 3841.7179999999935
      }
    }
  }
}