{
  "ts_col": "2025-10-15T22:44:38-05:00",
  "xau": {
    "swissquote": {
      "price": 4233.485,
      "bid": 4233.362,
      "ask": 4233.608,
      "ts_src": "2025-10-16T03:44:36+00:00",
      "ts_src_col": "2025-10-15T22:44:36-05:00",
      "platform": "SwissquoteCapitalMarkets",
      "server": "Live7",
      "profile": "elite",
      "note": "Swissquote mejor liquidez"
    },
    "institucional": {
      "price": 4233.485,
      "bid": null,
      "ask": null,
      "ts_src": null,
      "ts_src_col": null,
      "platform": null,
      "server": null,
      "profile": null,
      "note": "XAU: 100% Swissquote"
    },
    "volatility": {
      "atr_cc_14": 0.8423133862329523,
      "atr_pct": 0.01989645377822178,
      "range_24h_local": {
        "high": 4241.47,
        "low": 4230.19,
        "width": 11.280000000000655
      }
    }
  },
  "btc": {
    "coingecko": {
      "price": 111691.0,
      "bid": null,
      "ask": null,
      "ts_src": null,
      "ts_src_col": null,
      "platform": null,
      "server": null,
      "profile": null,
      "note": "CoinGecko simple/price"
    },
    "coinbase": {
      "price": 111644.815,
      "bid": null,
      "ask": null,
      "ts_src": null,
      "ts_src_col": null,
      "platform": null,
      "server": null,
      "profile": null,
      "note": "Coinbase Spot"
    },
    "institucional": {
      "price": 111672.526,
      "bid": null,
      "ask": null,
      "ts_src": null,
      "ts_src_col": null,
      "platform": null,
      "server": null,
      "profile": null,
      "note": "BTC: 60% CoinGecko + 40% Coinbase"
    },
    "volatility": {
      "atr_cc_14": 24.476773694269983,
      "atr_pct": 0.021918348738945857,
      "range_24h_local": {
        "high": 111782.486,
        "low": 111522.794,
        "width": 259.69200000001
      }
    }
  }
}