{
  "ts_col": "2025-10-16T09:35:52-05:00",
  "xau": {
    "swissquote": {
      "price": 4266.205,
      "bid": 4266.082,
      "ask": 4266.328,
      "ts_src": "2025-10-16T14:35:18+00:00",
      "ts_src_col": "2025-10-16T09:35:18-05:00",
      "platform": "SwissquoteCapitalMarkets",
      "server": "Live7",
      "profile": "elite",
      "note": "Swissquote mejor liquidez"
    },
    "institucional": {
      "price": 4266.205,
      "bid": null,
      "ask": null,
      "ts_src": null,
      "ts_src_col": null,
      "platform": null,
      "server": null,
      "profile": null,
      "note": "XAU: 100% Swissquote"
    },
    "volatility": {
      "atr_cc_14": 1.9009560007849313,
      "atr_pct": 0.04455847763492217,
      "range_24h_local": {
        "high": 4266.32,
        "low": 4233.395,
        "width": 32.92499999999927
      }
    }
  },
  "btc": {
    "coingecko": {
      "price": 110466.0,
      "bid": null,
      "ask": null,
      "ts_src": null,
      "ts_src_col": null,
      "platform": null,
      "server": null,
      "profile": null,
      "note": "CoinGecko simple/price"
    },
    "coinbase": {
      "price": 110433.73,
      "bid": null,
      "ask": null,
      "ts_src": null,
      "ts_src_col": null,
      "platform": null,
      "server": null,
      "profile": null,
      "note": "Coinbase Spot"
    },
    "institucional": {
      "price": 110453.09199999999,
      "bid": null,
      "ask": null,
      "ts_src": null,
      "ts_src_col": null,
      "platform": null,
      "server": null,
      "profile": null,
      "note": "BTC: 60% CoinGecko + 40% Coinbase"
    },
    "volatility": {
      "atr_cc_14": 66.86975694354643,
      "atr_pct": 0.06054131734360722,
      "range_24h_local": {
        "high": 111642.788,
        "low": 110060.45000000001,
        "width": 1582.3379999999888
      }
    }
  }
}