{
  "ts_col": "2025-10-16T05:33:15-05:00",
  "xau": {
    "swissquote": {
      "price": 4236.43,
      "bid": 4236.307,
      "ask": 4236.553,
      "ts_src": "2025-10-16T10:32:40+00:00",
      "ts_src_col": "2025-10-16T05:32:40-05:00",
      "platform": "SwissquoteCapitalMarkets",
      "server": "Live7",
      "profile": "elite",
      "note": "Swissquote mejor liquidez"
    },
    "institucional": {
      "price": 4236.43,
      "bid": null,
      "ask": null,
      "ts_src": null,
      "ts_src_col": null,
      "platform": null,
      "server": null,
      "profile": null,
      "note": "XAU: 100% Swissquote"
    },
    "volatility": {
      "atr_cc_14": 1.2229388280789308,
      "atr_pct": 0.02886720252851884,
      "range_24h_local": {
        "high": 4242.76,
        "low": 4216.235,
        "width": 26.525000000000546
      }
    }
  },
  "btc": {
    "coingecko": {
      "price": 111410.0,
      "bid": null,
      "ask": null,
      "ts_src": null,
      "ts_src_col": null,
      "platform": null,
      "server": null,
      "profile": null,
      "note": "CoinGecko simple/price"
    },
    "coinbase": {
      "price": 111472.045,
      "bid": null,
      "ask": null,
      "ts_src": null,
      "ts_src_col": null,
      "platform": null,
      "server": null,
      "profile": null,
      "note": "Coinbase Spot"
    },
    "institucional": {
      "price": 111434.818,
      "bid": null,
      "ask": null,
      "ts_src": null,
      "ts_src_col": null,
      "platform": null,
      "server": null,
      "profile": null,
      "note": "BTC: 60% CoinGecko + 40% Coinbase"
    },
    "volatility": {
      "atr_cc_14": 57.511865627941724,
      "atr_pct": 0.051610319521445916,
      "range_24h_local": {
        "high": 111782.486,
        "low": 109750.714,
        "width": 2031.7719999999972
      }
    }
  }
}